{
    "version": "1.0.84",
    "projectName": "Program VBot Offline",
    "description": "Thêm Cấu Hình Thiết Lập Wifi Thông Qua Bluetooth sử dụng App BTBerryWifi, Chi tiết Xem Trong Mục 'Hướng Dẫn' Của Giao Diện WebUI, Hoặc Truy Cập SSH Và Chạy Lệnh: $:> bash /home/pi/VBot_Offline/resource/set_wifi_via_ble/btwifisetInstall.sh",
    "releaseDate": "01/01/2026",
    "changes": [
        {
            "type": "feature",
            "description": "Cần Cài Bổ Sung Thư Viện Sau: 'pip install broadlink==0.19.0'"
        },
        {
            "type": "fix",
            "description": "Đã sửa tất cả các lỗi, và mang tới cho các bạn thêm vài lỗi nữa"
        },
        {
            "type": "improvement",
            "description": "Cải thiện độ ổn định, tiện tay vá luôn lỗ hổng ngoài không gian"
        }
    ],
    "author": "Vũ Tuyển",
    "status": "stable",
    "previousVersion": "1.0.0"
}